deidentifier/__init__.py
deidentifier/data.py
gc_deidentify-0.2.1.dist-info/METADATA
gc_deidentify-0.2.1.dist-info/WHEEL
gc_deidentify-0.2.1.dist-info/top_level.txt
gc_deidentify-0.2.1.dist-info/RECORD
