Metadata-Version: 2.1
Name: gc-deidentify
Version: 0.2.1
Summary: Deidentification helpers for python and SQL
Home-page: https://github.com/genesiscare/python-packages
Author: Nick Farrell
Author-email: nick.farrell@genesiscare.com
License: UNKNOWN
Project-URL: Bug Tracker, https://github.com/genesiscare/python-packages/issues
Platform: UNKNOWN
Classifier: Programming Language :: Python :: 3
Classifier: License :: OSI Approved :: MIT License
Classifier: Operating System :: OS Independent
Requires-Python: >=3.8
